{"_api_key_user":"123456789","_api_key_password":"1234","_api_data":{"1":{"_edited_on":"01\/02\/2015 20:57:12","first_name":"Robin","last_name":"DesBois Bois","movies_participate":{"1":{"_api_rsc_link":{"_name":"movie","_id":"1","_depot":"local"}}}},"2":{"_edited_on":"02\/02\/2015 11:21:44","first_name":"Robin","last_name":"DesBois","movies_participate":{"1":{"_api_rsc_link":{"_name":"movie","_id":"1","_depot":"local"}}}},"3":{"_edited_on":"04\/02\/2015 11:50:30","first_name":"Robin La tour","last_name":"DesBois","movies_participate":{"1":{"_api_rsc_link":{"_name":"movie","_id":"1","_depot":"local"}}}},"4":{"first_name":"Robin","last_name":"DesBois Bois","movies_participate":{"1":{"_api_rsc_link":{"_name":"movie","_id":"1","_depot":"local"}}},"_edited_on":"04\/14\/2015 09:04:00"},"5":{"first_name":"Robin","last_name":"DesBois Bois","movies_participate":{"1":{"_api_rsc_link":{"_name":"movie","_id":"1","_depot":"local"}}},"_edited_on":"04\/14\/2015 09:06:18"},"6":{"first_name":"Robin","last_name":"DesBois Bois","movies_participate":{"1":{"_api_rsc_link":{"_name":"movie","_id":"1","_depot":"local"}}},"_edited_on":"04\/14\/2015 09:29:17"},"7":{"first_name":"Robin","last_name":"DesBois Bois","movies_participate":{"1":{"_api_rsc_link":{"_name":"movie","_id":"1","_depot":"local"}}},"_edited_on":"04\/14\/2015 09:30:52"},"8":{"first_name":"Robin","last_name":"DesBois Bois","movies_participate":{"1":{"_api_rsc_link":{"_name":"movie","_id":"1","_depot":"local"}}},"_edited_on":"04\/14\/2015 10:13:41"},"9":{"first_name":"Robin","last_name":"DesBois Bois","movies_participate":{"1":{"_api_rsc_link":{"_name":"movie","_id":"1","_depot":"local"}}},"_edited_on":"04\/14\/2015 10:14:03"},"10":{"first_name":"Robin","last_name":"DesBois","movies_participate":{"1":{"_api_rsc_link":{"_name":"movie","_id":"1","_depot":"local"}}},"_edited_on":"04\/14\/2015 10:18:46"},"11":{"first_name":"Robin","last_name":"DesBois","movies_participate":{"1":{"_api_rsc_link":{"_name":"movie","_id":"1","_depot":"local"}}},"_edited_on":"04\/14\/2015 10:23:51"},"12":{"first_name":"Robin","last_name":"DesBois","movies_participate":{"1":{"_api_rsc_link":{"_name":"movie","_id":"1","_depot":"local"}}},"_edited_on":"04\/14\/2015 10:26:48"}}}